README.md
setup.py
edm/__init__.py
edm.egg-info/PKG-INFO
edm.egg-info/SOURCES.txt
edm.egg-info/dependency_links.txt
edm.egg-info/requires.txt
edm.egg-info/top_level.txt
edm/datastructures/__init__.py
edm/datastructures/data_structures.py
edm/metrics/__init__.py
edm/metrics/difficulty_measures.py
edm/report/__init__.py
edm/report/report_creator.py