Metadata-Version: 2.1
Name: edm
Version: 0.0.4
Summary: Tools for assessing the difficulty of datasets for machine learning models
Home-page: https://github.com/Wluper/edm
Author: Ed Collins
Author-email: ed@wluper.com
License: GPL v2
Platform: UNKNOWN
Requires-Python: ~=3.3
